rcsb/__init__.py
rcsb/utils/__init__.py
rcsb/utils/ccdc/CcdcGeomAnal.py
rcsb/utils/ccdc/CcdcSearch.py
rcsb/utils/ccdc/CcdcSearchExec.py
rcsb/utils/ccdc/CcdcSearchExecMp.py
rcsb/utils/ccdc/CcdcSearchMp.py
rcsb/utils/ccdc/__init__.py
rcsb.utils.ccdc-0.18.dist-info/LICENSE
rcsb.utils.ccdc-0.18.dist-info/METADATA
rcsb.utils.ccdc-0.18.dist-info/WHEEL
rcsb.utils.ccdc-0.18.dist-info/entry_points.txt
rcsb.utils.ccdc-0.18.dist-info/top_level.txt
rcsb.utils.ccdc-0.18.dist-info/RECORD
